nbutils/__init__.py
nbutils/__main__.py
nbutils/iter.py
neurobionic_utils-1.0.0.dist-info/LICENSE
neurobionic_utils-1.0.0.dist-info/METADATA
neurobionic_utils-1.0.0.dist-info/WHEEL
neurobionic_utils-1.0.0.dist-info/entry_points.txt
neurobionic_utils-1.0.0.dist-info/top_level.txt
neurobionic_utils-1.0.0.dist-info/RECORD
