Metadata-Version: 2.1
Name: neurobionic-utils
Version: 1.0.0
Summary: Utils for convenient python programming
Author-email: Neurobionic <info@neurobionic.ru>
License: Copyright (c) 2024 Neurobionic
Project-URL: Homepage, https://github.com/Neurobionic/nbcutils
Keywords: feed,reader,tutorial
Classifier: License :: OSI Approved :: MIT License
Classifier: Programming Language :: Python
Classifier: Programming Language :: Python :: 3
Requires-Python: >=3.9
License-File: LICENSE
Provides-Extra: dev
Requires-Dist: black; extra == "dev"
Requires-Dist: bumpver; extra == "dev"
Requires-Dist: isort; extra == "dev"
Requires-Dist: pip-tools; extra == "dev"
Requires-Dist: pytest; extra == "dev"
